<?xml version="1.0" encoding="UTF-8"?>
<!DOCTYPE mapper PUBLIC "-//mybatis.org//DTD Mapper 3.0//EN" "http://mybatis.org/dtd/mybatis-3-mapper.dtd">
<mapper namespace="com.gopair.chatservice.mapper.PrivateMessageMapper">

    <resultMap id="PrivateMessageVOMap" type="com.gopair.chatservice.domain.vo.PrivateMessageVO">
        <id column="id" property="messageId"/>
        <result column="conversation_id" property="conversationId"/>
        <result column="sender_id" property="senderId"/>
        <result column="receiver_id" property="receiverId"/>
        <result column="sender_nickname" property="senderNickname"/>
        <result column="sender_avatar" property="senderAvatar"/>
        <result column="message_type" property="messageType"/>
        <result column="message_type_desc" property="messageTypeDesc"/>
        <result column="content" property="content"/>
        <result column="file_url" property="fileUrl"/>
        <result column="file_name" property="fileName"/>
        <result column="file_size" property="fileSize"/>
        <result column="is_recalled" property="isRecalled"/>
        <result column="recalled_at" property="recalledAt"/>
        <result column="create_time" property="createTime"/>
    </resultMap>

    <sql id="PrivateMessageVOColumns">
        pm.id,
        pm.conversation_id,
        pm.sender_id,
        pm.receiver_id,
        u.nickname AS sender_nickname,
        u.avatar AS sender_avatar,
        pm.message_type,
        CASE pm.message_type
            WHEN 1 THEN '文本消息'
            WHEN 2 THEN '图片消息'
            WHEN 3 THEN '文件消息'
            ELSE '未知类型'
        END AS message_type_desc,
        pm.content,
        pm.file_url,
        pm.file_name,
        pm.file_size,
        pm.is_recalled,
        pm.recalled_at,
        pm.create_time
    </sql>

    <select id="selectMessageVOPage" resultMap="PrivateMessageVOMap">
        SELECT <include refid="PrivateMessageVOColumns"/>
        FROM private_message pm
        LEFT JOIN user u ON pm.sender_id = u.user_id
        WHERE pm.conversation_id = #{conversationId} AND pm.is_recalled = 0
        ORDER BY pm.create_time ASC
    </select>

    <select id="selectLatestMessageByConversation" resultMap="PrivateMessageVOMap">
        SELECT <include refid="PrivateMessageVOColumns"/>
        FROM private_message pm
        LEFT JOIN user u ON pm.sender_id = u.user_id
        WHERE pm.conversation_id = #{conversationId} AND pm.is_recalled = 0
        ORDER BY pm.create_time DESC
        LIMIT 1
    </select>

    <select id="selectConversationIdsByUser" resultType="java.lang.Long">
        SELECT t.conversation_id
        FROM (
          SELECT conversation_id, create_time,
            ROW_NUMBER() OVER (PARTITION BY conversation_id ORDER BY create_time DESC) AS rn
          FROM private_message
          WHERE (sender_id = #{userId} OR receiver_id = #{userId})
            AND is_recalled = 0
        ) t
        WHERE t.rn = 1
        ORDER BY t.create_time DESC
    </select>

    <select id="countByConversation" resultType="java.lang.Long">
        SELECT COUNT(1)
        FROM private_message
        WHERE conversation_id = #{conversationId} AND is_recalled = 0
    </select>

    <select id="selectConversationDetailsBatch" resultType="com.gopair.chatservice.domain.vo.ConversationDetailVO">
        SELECT
            conv.conversation_id AS conversationId,
            CASE WHEN latest.sender_id = #{userId} THEN latest.receiver_id ELSE latest.sender_id END AS friendId,
            u.nickname AS friendNickname,
            u.avatar AS friendAvatar,
            latest.content AS lastMessageContent,
            DATE_FORMAT(latest.create_time, '%Y-%m-%d %H:%i:%s') AS lastMessageTime,
            latest.message_type AS lastMessageType,
            conv.cnt AS messageCount
        FROM (
            SELECT conversation_id, COUNT(1) AS cnt
            FROM private_message
            WHERE (sender_id = #{userId} OR receiver_id = #{userId})
              AND is_recalled = 0
            GROUP BY conversation_id
        ) conv
        LEFT JOIN (
            SELECT pm2.*
            FROM private_message pm2
            INNER JOIN (
                SELECT conversation_id, MAX(create_time) AS max_time
                FROM private_message
                WHERE (sender_id = #{userId} OR receiver_id = #{userId})
                  AND is_recalled = 0
                GROUP BY conversation_id
            ) latest ON latest.conversation_id = pm2.conversation_id
                     AND latest.max_time = pm2.create_time
            WHERE pm2.is_recalled = 0
        ) latest ON latest.conversation_id = conv.conversation_id
        LEFT JOIN user u ON u.user_id = CASE WHEN latest.sender_id = #{userId} THEN latest.receiver_id ELSE latest.sender_id END
        ORDER BY latest.create_time DESC
    </select>

    <select id="selectMessageVOPageBefore" resultMap="PrivateMessageVOMap">
        SELECT <include refid="PrivateMessageVOColumns"/>
        FROM private_message pm
        LEFT JOIN user u ON pm.sender_id = u.user_id
        WHERE pm.conversation_id = #{conversationId}
          AND pm.is_recalled = 0
          <if test="beforeMessageId != null">
              AND (pm.create_time, pm.id) &lt; (SELECT create_time, id FROM private_message WHERE id = #{beforeMessageId})
          </if>
        ORDER BY pm.create_time DESC, pm.id DESC
        LIMIT #{pageSize}
    </select>

</mapper>
